{
  "response": [
    {
        "maintainer": "K Samba Siva Rao (KSSRAO)",
        "oem": "Realme",
        "device": "Realme 5 Pro",
        "filename": "riceDroid-12.1-2022071314-RMX1971-v3.0-PIXEL.zip",
        "download": "https://sourceforge.net/projects/ricedroid-rmx1971/files/3.0-Hotfix/riceDroid-12.1-2022071314-RMX1971-v3.0-PIXEL.zip/download",
        "timestamp": 1657683800,
        "md5": "f66f41b73a4bfed9dbcb714ca1d48492",
        "sha256": "da6d875eb4044f40614fb83f922ee1a4786f80b229a4ef8fa1ef5a5d57d49d8e",
        "size": 1640148408,
        "version": "3.0",
        "buildtype": "Monthly",
        "forum": "",
        "gapps": "",
        "firmware": "",
        "modem": "",
        "bootloader": "",
        "recovery": "",
        "paypal": "",
        "telegram": "https://t.me/kssrao13882",
        "dt": "https://github.com/riceDroid-Devices/device_realme_RMX1971",
        "common-dt": "https://github.com/riceDroid-Devices/device_realme_sdm710-common",
        "kernel": "https://gitlab.com/kssrao13882/kernel_realme_sdm710"
    }
  ]
}
